Workbook

Sheet 001 (2)
A1: Fondo | B1: Centro Gestor | C1: Posicion Presupuestaria | D1: Area Funcional | E1: Proyecto | F1: Nombre | G1: Ppto Inicial | H1: Reducciones | I1: Adiciones | J1: Creditos | K1: Contracreditos | L1: Total Ppto actual | M1: Disponibilidad | N1: Compromiso | O1: Factura | P1: Pagos | Q1: Disponible neto | R1: Ejecución | S1: % ejecucion
A2: 170000124 | B2: 25000000 CONCEJO | C2: 21101010010101 | D2: 00000.00000.0001 | E2: 1000000 | F2: programa de gastos | G2: 4922674791 | H2: 0 | I2: 150000000 | J2: 0 | K2: 150000000 | L2: 4922674791 | M2: 0 | N2: 329470 | O2: 0 | P2: 2755912594 | Q2: 2166432727 | R2: 2756242064 | S2: 55.99074
A3: 170000124 | B3: 25000000 CONCEJO | C3: 211010100102 | D3: 00000.00000.0001 | E3: 1000000 | F3: programa de gastos | G3: 741363710 | H3: 0 | I3: 0 | J3: 0 | K3: 0 | L3: 741363710 | M3: 0 | N3: 0 | O3: 0 | P3: 373751470 | Q3: 367612240 | R3: 373751470 | S3: 50.41405
A4: 170000124 | B4: 25000000 CONCEJO | C4: 211010100104 | D4: 00000.00000.0001 | E4: 1000000 | F4: programa de gastos | G4: 652993 | H4: 0 | I4: 0 | J4: 0 | K4: 0 | L4: 652993 | M4: 0 | N4: 0 | O4: 0 | P4: 0 | Q4: 652993 | R4: 0 | S4: 0
A5: 170000124 | B5: 25000000 CONCEJO | C5: 211010100105 | D5: 00000.00000.0001 | E5: 1000000 | F5: programa de gastos | G5: 1321030 | H5: 0 | I5: 0 | J5: 0 | K5: 0 | L5: 1321030 | M5: 0 | N5: 12 | O5: 0 | P5: 31038 | Q5: 1289980 | R5: 31050 | S5: 2.3504387
A6: 170000124 | B6: 25000000 CONCEJO | C6: 211010100106 | D6: 00000.00000.0001 | E6: 1000000 | F6: programa de gastos | G6: 248513854 | H6: 0 | I6: 30000000 | J6: 0 | K6: 0 | L6: 278513854 | M6: 0 | N6: 2557222 | O6: 0 | P6: 211882086 | Q6: 64074546 | R6: 214439308 | S6: 76.994126
A7: 170000124 | B7: 25000000 CONCEJO | C7: 211010100107 | D7: 00000.00000.0001 | E7: 1000000 | F7: programa de gastos | G7: 183209198 | H7: 0 | I7: 25000000 | J7: 0 | K7: 0 | L7: 208209198 | M7: 0 | N7: 754348 | O7: 0 | P7: 82905092 | Q7: 124549758 | R7: 83659440 | S7: 40.180473
A8: 170000124 | B8: 25000000 CONCEJO | C8: 21101010010801 | D8: 00000.00000.0001 | E8: 1000000 | F8: programa de gastos | G8: 483545245 | H8: 0 | I8: 30000000 | J8: 0 | K8: 0 | L8: 513545245 | M8: 0 | N8: 2789829 | O8: 0 | P8: 3525870 | Q8: 507229546 | R8: 6315699 | S8: 1.2298233
A9: 170000124 | B9: 25000000 CONCEJO | C9: 21101010010802 | D9: 00000.00000.0001 | E9: 1000000 | F9: programa de gastos | G9: 262631398 | H9: 0 | I9: 20000000 | J9: 0 | K9: 0 | L9: 282631398 | M9: 0 | N9: 1154989 | O9: 0 | P9: 125273551 | Q9: 156202858 | R9: 126428540 | S9: 44.732659
A10: 170000124 | B10: 25000000 CONCEJO | C10: 21101010021202 | D10: 00000.00000.0001 | E10: 1000000 | F10: programa de gastos | G10: 12659 | H10: 0 | I10: 0 | J10: 0 | K10: 0 | L10: 12659 | M10: 0 | N10: 0 | O10: 0 | P10: 0 | Q10: 12659 | R10: 0 | S10: 0
A11: 170000124 | B11: 25000000 CONCEJO | C11: 2110102001 | D11: 00000.00000.0001 | E11: 1000000 | F11: programa de gastos | G11: 752446180 | H11: 0 | I11: 0 | J11: 0 | K11: 0 | L11: 752446180 | M11: 0 | N11: 200 | O11: 0 | P11: 397520621 | Q11: 354925359 | R11: 397520821 | S11: 52.830466
A12: 170000124 | B12: 25000000 CONCEJO | C12: 2110102002 | D12: 00000.00000.0001 | E12: 1000000 | F12: programa de gastos | G12: 538388215 | H12: 0 | I12: 0 | J12: 0 | K12: 0 | L12: 538388215 | M12: 0 | N12: 400 | O12: 0 | P12: 284092600 | Q12: 254295215 | R12: 284093000 | S12: 52.767314
A13: 170000124 | B13: 25000000 CONCEJO | C13: 2110102003 | D13: 00000.00000.0001 | E13: 1000000 | F13: programa de gastos | G13: 289463182 | H13: 0 | I13: 0 | J13: 230000000 | K13: 0 | L13: 519463182 | M13: 0 | N13: 0 | O13: 0 | P13: 517117161 | Q13: 2346021 | R13: 517117161 | S13: 99.548376
... A4747: 110090124 | B4747: 77100000 Gerencia | C4747: 2320202008 | D4747: 32080900.3811.99 | E4747: 200429 | F4747: DESARROLLO BRIGADAS SANITARIA | G4747: 445000000 | H4747: 0 | I4747: 0 | J4747: 0 | K4747: 0 | L4747: 445000000 | M4747: 0 | N4747: 325010011 | O4747: 0 | P4747: 1840000 | Q4747: 118149989 | R4747: 326850011 | S4747: 73.449441
G4748: =SUM(G2:G4747) -> 8478294440042 | H4748: =SUM(H2:H4747) -> 231315799045 | I4748: =SUM(I2:I4747) -> 1837008468722 | J4748: =SUM(J2:J4747) -> 652234503891 | K4748: =SUM(K2:K4747) -> 652234503891 | L4748: =SUM(L2:L4747) -> 10083987109719 | M4748: =SUM(M2:M4747) -> 1164439924885 | N4748: =SUM(N2:N4747) -> 1431790522532 | ... R4748: =SUM(R2:R4747) -> 6184632798947 | S4748: =+R4748/L4748*100 -> 61.331225
G4750: 8478294440042 | H4750: -231315799045 | I4750: 1837008468722 | J4750: 652234503891 | K4750: -652234503891 | L4750: 10083987109719 | M4750: 1164439924885 | N4750: 1431790522532 | O4750: 185829041 | P4750: 4752656447374 | Q4750: -2734914385887 | R4750: 6184632798947 | S4750: 61.3312
G4752: =+G4748-G4750 -> 0 | H4752: =+H4748+H4750 -> 0 | I4752: =+I4748-I4750 -> 0 | J4752: =+J4748-J4750 -> 0 | K4752: =+K4748+K4750 -> 0 | L4752: =+L4748-L4750 -> 0 | M4752: =+M4748-M4750 -> 0 | N4752: =+N4748-N4750 -> 0 | O4752: =+O4748-O4750 -> 0 | P4752: =+P4748-P4750 -> 0 | Q4752: =+Q4748+Q4750 -> 0 | R4752: =+R4748-R4750 -> 0 | S4752: =+S4748-S4750 -> 2.4759165e-05

Sheet ejecucion
A1: Fondo | B1: CentroGestor | C1: PosicionPresupuestaria | D1: AreaFuncional | E1: Proyecto | F1: Nombre | G1: Ppto_Inicial | H1: Reducciones | I1: Adiciones | J1: Creditos | K1: Contracreditos | L1: TotalPptoactual | M1: Disponibilidad | N1: Compromiso | O1: Factura | P1: Pagos | Q1: Disponibleneto | R1: Ejecucion | S1: porcejecucion | T1: mes_ejecucion | U1: vigencia
A2: 110070123 | B2: 70100000 | C2: 2320202008 | D2: 45991000.3918.99 | E2: 200332 | F2: FORTALECIMIENTO ALCALDÍA INST | G2: 0 | H2: 0 | I2: 46088721 | J2: 0 | K2: 46088721 | L2: 0 | M2: 0 | N2: 0 | O2: 0 | P2: 0 | Q2: 0 | R2: 0 | S2: 0 | T2: 6 | U2: 2024
A3: 110070124 | B3: 70100000 | C3: 2320202006 | D3: 45991000.3918.99 | E3: 200332 | F3: FORTALECIMIENTO ALCALDÍA INST | G3: 167438906 | H3: 0 | I3: 0 | J3: 0 | K3: 0 | L3: 167438906 | M3: 0 | N3: 0 | O3: 0 | P3: 0 | Q3: 167438906 | R3: 0 | S3: 0 | T3: 6 | U3: 2024
A4: 110070124 | B4: 70100000 | C4: 2320202008 | D4: 45991000.3918.99 | E4: 200332 | F4: FORTALECIMIENTO ALCALDÍA INST | G4: 800000000 | H4: 0 | I4: 0 | J4: 0 | K4: 0 | L4: 800000000 | M4: 0 | N4: 0 | O4: 0 | P4: 500000000 | Q4: 300000000 | R4: 500000000 | S4: 62.5 | T4: 6 | U4: 2024
A5: 110090124 | B5: 70100000 | C5: 2320202008 | D5: 45991000.3918.99 | E5: 200332 | F5: FORTALECIMIENTO ALCALDÍA INST | G5: 560691247 | H5: 0 | I5: 0 | J5: 273800525 | K5: 0 | L5: 834491772 | M5: 1690401 | N5: 461612532 | O5: 0 | P5: 149610165 | Q5: 221578674 | R5: 611222697 | S5: 73.244904 | T5: 6 | U5: 2024
A6: 110090124 | B6: 70100000 | C6: 2320202009 | D6: 45991000.3918.99 | E6: 200332 | F6: FORTALECIMIENTO ALCALDÍA INST | G6: 273800525 | H6: 0 | I6: 0 | J6: 0 | K6: 273800525 | L6: 0 | M6: 0 | N6: 0 | O6: 0 | P6: 0 | Q6: 0 | R6: 0 | S6: 0 | T6: 6 | U6: 2024
A7: 110070123 | B7: 70100000 | C7: 2320202006 | D7: 45991000.3918.99 | E7: 200345 | F7: ADMINIST UNIDAD CUMPL PROY ES | G7: 0 | H7: 0 | I7: 46035033 | J7: 0 | K7: 46035033 | L7: 0 | M7: 0 | N7: 0 | O7: 0 | P7: 0 | Q7: 0 | R7: 0 | S7: 0 | T7: 6 | U7: 2024
A8: 110070124 | B8: 70100000 | C8: 2320202006 | D8: 45991000.3918.99 | E8: 200345 | F8: ADMINIST UNIDAD CUMPL PROY ES | G8: 80000000 | H8: 0 | I8: 0 | J8: 0 | K8: 0 | L8: 80000000 | M8: 0 | N8: 0 | O8: 0 | P8: 0 | Q8: 80000000 | R8: 0 | S8: 0 | T8: 6 | U8: 2024
A9: 110070124 | B9: 70100000 | C9: 2320202008 | D9: 45991000.3918.99 | E9: 200345 | F9: ADMINIST UNIDAD CUMPL PROY ES | G9: 620000000 | H9: 0 | I9: 0 | J9: 0 | K9: 0 | L9: 620000000 | M9: 0 | N9: 0 | O9: 0 | P9: 200000000 | Q9: 420000000 | R9: 200000000 | S9: 32.258065 | T9: 6 | U9: 2024
A10: 160070123 | B10: 70100000 | C10: 2320202006 | D10: 45991000.3918.99 | E10: 200345 | F10: ADMINIST UNIDAD CUMPL PROY ES | G10: 0 | H10: 0 | I10: 21467328 | J10: 0 | K10: 0 | L10: 21467328 | M10: 0 | N10: 3927536 | O10: 0 | P10: 17539792 | Q10: 0 | R10: 21467328 | S10: 100 | T10: 6 | U10: 2024
A11: 110090124 | B11: 70100000 | C11: 2320202008 | D11: 45991000.3918.99 | E11: 200366 | F11: FORTAL CONGLOM GOBIERNO CORPO | G11: 402500000 | H11: 0 | I11: 0 | J11: 0 | K11: 0 | L11: 402500000 | M11: 1942600 | N11: 271617921 | O11: 0 | P11: 113620508 | Q11: 15318971 | R11: 385238429 | S11: 95.711411 | T11: 6 | U11: 2024
A12: 110004010 | B12: 70200000 | C12: 2320202009 | D12: 45991000.3918.99 | E12: 080527 | F12: DISEÑO Y DESARROLLO DE POLÍTI | G12: 0 | H12: 0 | I12: 15000000 | J12: 0 | K12: 0 | L12: 15000000 | M12: 0 | N12: 0 | O12: 0 | P12: 0 | Q12: 15000000 | R12: 0 | S12: 0 | T12: 6 | U12: 2024
A13: 110090124 | B13: 70200000 | C13: 2320202009 | D13: 45991000.3307.99 | E13: 200359 | F13: FORTAL REDES CIUD Y DE DEPEND | G13: 520000000 | H13: 0 | I13: 0 | J13: 0 | K13: 0 | L13: 520000000 | M13: 0 | N13: 9654140 | O13: 0 | P13: 129345860 | Q13: 381000000 | R13: 139000000 | S13: 26.730769 | T13: 6 | U13: 2024
... A3959: 110070124 | B3959: 77100000 | C3959: 2320202008 | D3959: 40021400.4518.10 | E3959: 200433 | F3959: GENERACIÓN DE ALIANZAS SOCIOC | G3959: 507803000 | H3959: 0 | I3959: 0 | J3959: 0 | K3959: 0 | L3959: 507803000 | M3959: 0 | N3959: 475790000 | O3959: 0 | P3959: 0 | Q3959: 32013000 | R3959: 475790000 | S3959: 93.695784 | T3959: 6 | U3959: 2024

Sheet EJECUCION JULIO
A1: Fondo | B1: CentroGestor | C1: PosicionPresupuestaria | D1: AreaFuncional | E1: Proyecto | F1: Nombre | G1: Ppto_Inicial | H1: Reducciones | I1: Adiciones | J1: Creditos | K1: Contracreditos | L1: TotalPptoactual | M1: Disponibilidad | N1: Compromiso | O1: Factura | P1: Pagos | Q1: Disponibleneto | R1: Ejecucion | S1: porcejecucion | T1: mes_ejecucion | U1: vigencia
A2: 110070123 | B2: 70100000 Secretar | C2: 2320202008 | D2: 45991000.3918.99 | E2: 200332 | F2: FORTALECIMIENTO ALCALDÍA INST | G2: 0 | H2: 0 | I2: 46088721 | J2: 0 | K2: 46088721 | L2: 0 | M2: 0 | N2: 0 | O2: 0 | P2: 0 | Q2: 0 | R2: 0 | S2: 0 | T2: 7 | U2: 2024
A3: 110070124 | B3: 70100000 Secretar | C3: 2320202006 | D3: 45991000.3918.99 | E3: 200332 | F3: FORTALECIMIENTO ALCALDÍA INST | G3: 167438906 | H3: 0 | I3: 0 | J3: 0 | K3: 0 | L3: 167438906 | M3: 0 | N3: 0 | O3: 0 | P3: 0 | Q3: 167438906 | R3: 0 | S3: 0 | T3: 7 | U3: 2024
A4: 110070124 | B4: 70100000 Secretar | C4: 2320202008 | D4: 45991000.3918.99 | E4: 200332 | F4: FORTALECIMIENTO ALCALDÍA INST | G4: 800000000 | H4: 0 | I4: 0 | J4: 0 | K4: 0 | L4: 800000000 | M4: 0 | N4: 0 | O4: 0 | P4: 500000000 | Q4: 300000000 | R4: 500000000 | S4: 62.5 | T4: 7 | U4: 2024
A5: 110090124 | B5: 70100000 Secretar | C5: 2320202008 | D5: 45991000.3918.99 | E5: 200332 | F5: FORTALECIMIENTO ALCALDÍA INST | G5: 560691247 | H5: 0 | I5: 0 | J5: 273800525 | K5: 0 | L5: 834491772 | M5: 1690401 | N5: 407079585 | O5: 0 | P5: 204143112 | Q5: 221578674 | R5: 611222697 | S5: 73.244904 | T5: 7 | U5: 2024
A6: 110090124 | B6: 70100000 Secretar | C6: 2320202009 | D6: 45991000.3918.99 | E6: 200332 | F6: FORTALECIMIENTO ALCALDÍA INST | G6: 273800525 | H6: 0 | I6: 0 | J6: 0 | K6: 273800525 | L6: 0 | M6: 0 | N6: 0 | O6: 0 | P6: 0 | Q6: 0 | R6: 0 | S6: 0 | T6: 7 | U6: 2024
A7: 110070123 | B7: 70100000 Secretar | C7: 2320202006 | D7: 45991000.3918.99 | E7: 200345 | F7: ADMINIST UNIDAD CUMPL PROY ES | G7: 0 | H7: 0 | I7: 46035033 | J7: 0 | K7: 46035033 | L7: 0 | M7: 0 | N7: 0 | O7: 0 | P7: 0 | Q7: 0 | R7: 0 | S7: 0 | T7: 7 | U7: 2024
A8: 110070124 | B8: 70100000 Secretar | C8: 2320202006 | D8: 45991000.3918.99 | E8: 200345 | F8: ADMINIST UNIDAD CUMPL PROY ES | G8: 80000000 | H8: 0 | I8: 0 | J8: 0 | K8: 0 | L8: 80000000 | M8: 0 | N8: 0 | O8: 0 | P8: 0 | Q8: 80000000 | R8: 0 | S8: 0 | T8: 7 | U8: 2024
A9: 110070124 | B9: 70100000 Secretar | C9: 2320202008 | D9: 45991000.3918.99 | E9: 200345 | F9: ADMINIST UNIDAD CUMPL PROY ES | G9: 620000000 | H9: 0 | I9: 0 | J9: 0 | K9: 0 | L9: 620000000 | M9: 0 | N9: 0 | O9: 0 | P9: 200000000 | Q9: 420000000 | R9: 200000000 | S9: 32.258065 | T9: 7 | U9: 2024
A10: 160070123 | B10: 70100000 Secretar | C10: 2320202006 | D10: 45991000.3918.99 | E10: 200345 | F10: ADMINIST UNIDAD CUMPL PROY ES | G10: 0 | H10: 0 | I10: 21467328 | J10: 0 | K10: 0 | L10: 21467328 | M10: 0 | N10: 3927536 | O10: 0 | P10: 17539792 | Q10: 0 | R10: 21467328 | S10: 100 | T10: 7 | U10: 2024
A11: 110090124 | B11: 70100000 Secretar | C11: 2320202008 | D11: 45991000.3918.99 | E11: 200366 | F11: FORTAL CONGLOM GOBIERNO CORPO | G11: 402500000 | H11: 0 | I11: 0 | J11: 0 | K11: 0 | L11: 402500000 | M11: 1942600 | N11: 233640918 | O11: 0 | P11: 151597511 | Q11: 15318971 | R11: 385238429 | S11: 95.711411 | T11: 7 | U11: 2024
A12: 110004010 | B12: 70200000 Secretar | C12: 2320202009 | D12: 45991000.3918.99 | E12: 080527 | F12: DISEÑO Y DESARROLLO DE POLÍTI | G12: 0 | H12: 0 | I12: 15000000 | J12: 0 | K12: 0 | L12: 15000000 | M12: 0 | N12: 0 | O12: 0 | P12: 0 | Q12: 15000000 | R12: 0 | S12: 0 | T12: 7 | U12: 2024
A13: 110090124 | B13: 70200000 Secretar | C13: 2320202009 | D13: 45991000.3307.99 | E13: 200359 | F13: FORTAL REDES CIUD Y DE DEPEND | G13: 520000000 | H13: 0 | I13: 0 | J13: 0 | K13: 0 | L13: 520000000 | M13: 0 | N13: 109654140 | O13: 0 | P13: 129345860 | Q13: 281000000 | R13: 239000000 | S13: 45.961538 | T13: 7 | U13: 2024
... A4026: 110070124 | B4026: 77100000 Gerencia | C4026: 2320202008 | D4026: 40021400.4518.10 | E4026: 200433 | F4026: GENERACIÓN DE ALIANZAS SOCIOC | G4026: 507803000 | H4026: 0 | I4026: 0 | J4026: 0 | K4026: 0 | L4026: 507803000 | M4026: 0 | N4026: 181258338 | O4026: 0 | P4026: 294531662 | Q4026: 32013000 | R4026: 475790000 | S4026: 93.695784 | T4026: 7 | U4026: 2024

Sheet tbl_proyectos_main
A1: Centro Gestor | B1: Proyecto | C1: Nombre | D1: dep
A2: 70100000 Secretar | B2: 200332 | C2: FORTALECIMIENTO ALCALDÍA INST | D2: =+MID(A2,1,3) -> 701
A3: 70100000 Secretar | B3: 200345 | C3: ADMINIST UNIDAD CUMPL PROY ES | D3: =+MID(A3,1,3) -> 701
A4: 70100000 Secretar | B4: 200366 | C4: FORTAL CONGLOM GOBIERNO CORPO | D4: =+MID(A4,1,3) -> 701
A5: 70200000 Secretar | B5: 080527 | C5: DISEÑO Y DESARROLLO DE POLÍTI | D5: =+MID(A5,1,3) -> 702
A6: 70200000 Secretar | B6: 200359 | C6: FORTAL REDES CIUD Y DE DEPEND | D6: =+MID(A6,1,3) -> 702
A7: 70200000 Secretar | B7: 200365 | C7: ASESORÍA ESTRAT COMUNICA DIVU | D7: =+MID(A7,1,3) -> 702
A8: 70200000 Secretar | B8: 200410 | C8: FORT ENCUENTRO PROCESOS Y MED | D8: =+MID(A8,1,3) -> 702
A9: 70200000 Secretar | B9: 230058 | C9: 24PP99-FORT PROC MEDIOS COMUN | D9: =+MID(A9,1,3) -> 702
A10: 70300000 Secretar | B10: 200428 | C10: MEJORAMI SISTEMA CONTROL INTE | D10: =+MID(A10,1,3) -> 703
A11: 70400000 Secretar | B11: 040320 | C11: Acuerdo Metro | D11: =+MID(A11,1,3) -> 704
A12: 70400000 Secretar | B12: 130355 | C12: Paso desnivel Tesoro via Lina | D12: =+MID(A12,1,3) -> 704
A13: 70400000 Secretar | B13: 200074 | C13: Apoyo en la formación de tale | D13: =+MID(A13,1,3) -> 704
... A515: 77100000 Gerencia | B515: 200433 | C515: GENERACIÓN DE ALIANZAS SOCIOC | D515: =+MID(A515,1,3) -> 771
D516: =+MID(A516,1,3)
D517: =+MID(A517,1,3)
D518: =+MID(A518,1,3)
D519: =+MID(A519,1,3)
D520: =+MID(A520,1,3)
D521: =+MID(A521,1,3)
D522: =+MID(A522,1,3)
D523: =+MID(A523,1,3)
D524: =+MID(A524,1,3)
D525: =+MID(A525,1,3)
D526: =+MID(A526,1,3)
D527: =+MID(A527,1,3)
... D1901: =+MID(A1901,1,3)

Sheet Hoja2
A1: Centro Gestor | B1: Proyecto | C1: Nombre | D1: dep | E1: Ppto_Inicial
A2: 70100000 Secretar | B2: 200332 | C2: FORTALECIMIENTO ALCALDÍA INST | D2: =+MID(A2,1,3) -> 701 | E2: =+SUMIF('EJECUCION JULIO'!$E:$E,tbl_proyectos_main!B2,'EJECUCION JULIO'!$G:$G) -> 1801930678
A3: 70100000 Secretar | B3: 200345 | C3: ADMINIST UNIDAD CUMPL PROY ES | D3: =+MID(A3,1,3) -> 701 | E3: =+SUMIF('EJECUCION JULIO'!$E:$E,tbl_proyectos_main!B3,'EJECUCION JULIO'!$G:$G) -> 700000000
A4: 70100000 Secretar | B4: 200366 | C4: FORTAL CONGLOM GOBIERNO CORPO | D4: =+MID(A4,1,3) -> 701 | E4: =+SUMIF('EJECUCION JULIO'!$E:$E,tbl_proyectos_main!B4,'EJECUCION JULIO'!$G:$G) -> 402500000
A5: 70200000 Secretar | B5: 080527 | C5: DISEÑO Y DESARROLLO DE POLÍTI | D5: =+MID(A5,1,3) -> 702 | E5: =+SUMIF('EJECUCION JULIO'!$E:$E,tbl_proyectos_main!B5,'EJECUCION JULIO'!$G:$G) -> 0
A6: 70200000 Secretar | B6: 200359 | C6: FORTAL REDES CIUD Y DE DEPEND | D6: =+MID(A6,1,3) -> 702 | E6: =+SUMIF('EJECUCION JULIO'!$E:$E,tbl_proyectos_main!B6,'EJECUCION JULIO'!$G:$G) -> 520000000
A7: 70200000 Secretar | B7: 200365 | C7: ASESORÍA ESTRAT COMUNICA DIVU | D7: =+MID(A7,1,3) -> 702 | E7: =+SUMIF('EJECUCION JULIO'!$E:$E,tbl_proyectos_main!B7,'EJECUCION JULIO'!$G:$G) -> 8097722711
A8: 70200000 Secretar | B8: 200410 | C8: FORT ENCUENTRO PROCESOS Y MED | D8: =+MID(A8,1,3) -> 702 | E8: =+SUMIF('EJECUCION JULIO'!$E:$E,tbl_proyectos_main!B8,'EJECUCION JULIO'!$G:$G) -> 1500000000
A9: 70200000 Secretar | B9: 230058 | C9: 24PP99-FORT PROC MEDIOS COMUN | D9: =+MID(A9,1,3) -> 702 | E9: =+SUMIF('EJECUCION JULIO'!$E:$E,tbl_proyectos_main!B9,'EJECUCION JULIO'!$G:$G) -> 6488896605
A10: 70300000 Secretar | B10: 200428 | C10: MEJORAMI SISTEMA CONTROL INTE | D10: =+MID(A10,1,3) -> 703 | E10: =+SUMIF('EJECUCION JULIO'!$E:$E,tbl_proyectos_main!B10,'EJECUCION JULIO'!$G:$G) -> 968143559
A11: 70400000 Secretar | B11: 040320 | C11: Acuerdo Metro | D11: =+MID(A11,1,3) -> 704 | E11: =+SUMIF('EJECUCION JULIO'!$E:$E,tbl_proyectos_main!B11,'EJECUCION JULIO'!$G:$G) -> 82373621752
A12: 70400000 Secretar | B12: 130355 | C12: Paso desnivel Tesoro via Lina | D12: =+MID(A12,1,3) -> 704 | E12: =+SUMIF('EJECUCION JULIO'!$E:$E,tbl_proyectos_main!B12,'EJECUCION JULIO'!$G:$G) -> 1467466049
A13: 70400000 Secretar | B13: 200074 | C13: Apoyo en la formación de tale | D13: =+MID(A13,1,3) -> 704 | E13: =+SUMIF('EJECUCION JULIO'!$E:$E,tbl_proyectos_main!B13,'EJECUCION JULIO'!$G:$G) -> 8202818232
... A515: 77100000 Gerencia | B515: 200433 | C515: GENERACIÓN DE ALIANZAS SOCIOC | D515: =+MID(A515,1,3) -> 771 | E515: =+SUMIF('EJECUCION JULIO'!$E:$E,tbl_proyectos_main!B515,'EJECUCION JULIO'!$G:$G) -> 507803000
D516: =+MID(A516,1,3) | E516: =+SUMIF('EJECUCION JULIO'!$E:$E,tbl_proyectos_main!B516,'EJECUCION JULIO'!$G:$G) -> 0
D517: =+MID(A517,1,3) | E517: =+SUMIF('EJECUCION JULIO'!$E:$E,tbl_proyectos_main!B517,'EJECUCION JULIO'!$G:$G) -> 0
D518: =+MID(A518,1,3) | E518: =+SUMIF('EJECUCION JULIO'!$E:$E,tbl_proyectos_main!B518,'EJECUCION JULIO'!$G:$G) -> 0
D519: =+MID(A519,1,3) | E519: =+SUMIF('EJECUCION JULIO'!$E:$E,tbl_proyectos_main!B519,'EJECUCION JULIO'!$G:$G) -> 0
D520: =+MID(A520,1,3) | E520: =+SUMIF('EJECUCION JULIO'!$E:$E,tbl_proyectos_main!B520,'EJECUCION JULIO'!$G:$G) -> 0
D521: =+MID(A521,1,3) | E521: =+SUMIF('EJECUCION JULIO'!$E:$E,tbl_proyectos_main!B521,'EJECUCION JULIO'!$G:$G) -> 0
D522: =+MID(A522,1,3) | E522: =+SUMIF('EJECUCION JULIO'!$E:$E,tbl_proyectos_main!B522,'EJECUCION JULIO'!$G:$G) -> 0
D523: =+MID(A523,1,3) | E523: =+SUMIF('EJECUCION JULIO'!$E:$E,tbl_proyectos_main!B523,'EJECUCION JULIO'!$G:$G) -> 0
D524: =+MID(A524,1,3) | E524: =+SUMIF('EJECUCION JULIO'!$E:$E,tbl_proyectos_main!B524,'EJECUCION JULIO'!$G:$G) -> 0
D525: =+MID(A525,1,3) | E525: =+SUMIF('EJECUCION JULIO'!$E:$E,tbl_proyectos_main!B525,'EJECUCION JULIO'!$G:$G) -> 0
D526: =+MID(A526,1,3) | E526: =+SUMIF('EJECUCION JULIO'!$E:$E,tbl_proyectos_main!B526,'EJECUCION JULIO'!$G:$G) -> 0
D527: =+MID(A527,1,3) | E527: =+SUMIF('EJECUCION JULIO'!$E:$E,tbl_proyectos_main!B527,'EJECUCION JULIO'!$G:$G) -> 0
... D1901: =+MID(A1901,1,3) | E1901: =+SUMIF('EJECUCION JULIO'!$E:$E,tbl_proyectos_main!B1901,'EJECUCION JULIO'!$G:$G) -> 0
